qsct/__init__.py
qsct/functions.py
qsct/main.py
qsct/obj_method.py
tests/__init__.py
tests/listener_test.py
tests/send_test.py
tests/test_functions.py
tests/test_obj_serv.py
tests/tets_obj_send.py
qsct_hs-0.0.3.dist-info/LICENSE
qsct_hs-0.0.3.dist-info/METADATA
qsct_hs-0.0.3.dist-info/WHEEL
qsct_hs-0.0.3.dist-info/top_level.txt
qsct_hs-0.0.3.dist-info/RECORD
