Metadata-Version: 2.1
Name: qsct-hs
Version: 0.0.3
Summary: UNKNOWN
Author: PunchyArchy
Author-email: ksmdrmvscthny@gmail.com
License: UNKNOWN
Platform: UNKNOWN
License-File: LICENSE
